sim_db/__init__.py
sim_db/__main__.py
sim_db/sdb
sim_db/sim_db
sim_db/sim_db_lib.py
sim_db/src_command_line_tool/__init__.py
sim_db/src_command_line_tool/add_command_line_tool_to_path.py
sim_db/src_command_line_tool/command_line_tool.py
sim_db/src_command_line_tool/commands/__init__.py
sim_db/src_command_line_tool/commands/add_and_run.py
sim_db/src_command_line_tool/commands/add_and_submit.py
sim_db/src_command_line_tool/commands/add_column.py
sim_db/src_command_line_tool/commands/add_comment.py
sim_db/src_command_line_tool/commands/add_package_root_to_path.py
sim_db/src_command_line_tool/commands/add_range_sim.py
sim_db/src_command_line_tool/commands/add_sim.py
sim_db/src_command_line_tool/commands/cd_results_dir.py
sim_db/src_command_line_tool/commands/combine_dbs.py
sim_db/src_command_line_tool/commands/default_settings.txt
sim_db/src_command_line_tool/commands/delete_empty_columns.py
sim_db/src_command_line_tool/commands/delete_results_dir.py
sim_db/src_command_line_tool/commands/delete_sim.py
sim_db/src_command_line_tool/commands/duplicate_and_run.py
sim_db/src_command_line_tool/commands/duplicate_delete_and_run.py
sim_db/src_command_line_tool/commands/duplicate_sim.py
sim_db/src_command_line_tool/commands/extract_params.py
sim_db/src_command_line_tool/commands/get.py
sim_db/src_command_line_tool/commands/helpers.py
sim_db/src_command_line_tool/commands/init.py
sim_db/src_command_line_tool/commands/list_commands.py
sim_db/src_command_line_tool/commands/list_print_configs.py
sim_db/src_command_line_tool/commands/print_sim.py
sim_db/src_command_line_tool/commands/run_serial_sims.py
sim_db/src_command_line_tool/commands/run_sim.py
sim_db/src_command_line_tool/commands/settings.py
sim_db/src_command_line_tool/commands/submit_sim.py
sim_db/src_command_line_tool/commands/update_sim.py
sim_db-0.2.9.data/scripts/sdb
sim_db-0.2.9.data/scripts/sim_db
sim_db-0.2.9.dist-info/DESCRIPTION.rst
sim_db-0.2.9.dist-info/METADATA
sim_db-0.2.9.dist-info/RECORD
sim_db-0.2.9.dist-info/WHEEL
sim_db-0.2.9.dist-info/entry_points.txt
sim_db-0.2.9.dist-info/metadata.json
sim_db-0.2.9.dist-info/top_level.txt
