Metadata-Version: 2.0
Name: sim-db
Version: 0.2.9
Summary: A database for simulation parameters.
Home-page: http://sim-db.readthedocs.io
Author: Hakon Austlid Tasken
Author-email: hakon.tasken@gmail.com
License: MIT License
Platform: UNKNOWN
Classifier: Programming Language :: Python
Classifier: Programming Language :: Python :: 2
Classifier: Programming Language :: Python :: 3
Classifier: License :: OSI Approved :: MIT License
